dwdGribExtractor/__init__.py
dwdGribExtractor/icon.py
dwdGribExtractor-0.0.7.dist-info/LICENSE
dwdGribExtractor-0.0.7.dist-info/METADATA
dwdGribExtractor-0.0.7.dist-info/WHEEL
dwdGribExtractor-0.0.7.dist-info/top_level.txt
dwdGribExtractor-0.0.7.dist-info/RECORD
