Metadata-Version: 2.1
Name: dwdGribExtractor
Version: 0.0.7
Summary: API for DWD's open weather grib data.
Home-page: https://github.com/prayer007/dwdGribExtractor
Author: Manuel Strohmaier
Author-email: manuel.strohmaier@joanneum.at
License: UNKNOWN
Project-URL: Documentation, https://github.com/prayer007/dwdGribExtractor
Platform: UNKNOWN
Classifier: Programming Language :: Python :: 3
Classifier: License :: OSI Approved :: MIT License
Classifier: Operating System :: OS Independent
Requires-Python: >=3.8
License-File: LICENSE
Requires-Dist: requests (>=2.25.1)
Requires-Dist: multiprocess (>=0.70.11.1)
Requires-Dist: xarray (>=0.16.2)
Requires-Dist: pandas (>=1.2.0)
Requires-Dist: cfgrib (>=0.9.9.0)
Requires-Dist: eccodes (>=1.2.0)
Requires-Dist: netCDF4 (>=1.5.6)
